pandocproj/__init__.py
pandocproj/__main__.py
pandocproj/data/__init__.py
pandocproj/data/bootstrap/fig/Vought_F4U_Corsair_(USMC).jpg
pandocproj/data/bootstrap/pandoc_tpl.md
pandocproj/data/bootstrap/static/mytable.csv
pandocproj/data/default-style/default.latex
pandocproj/data/default-style/fig/coverpage.pdf
pandocproj/data/default-style/fig/coverpage.svg
pandocproj/data/default-style/styling.css
pandocproj/data/default-style/styling.latex
pandocproj/data/makefile
pandocproj/utils.py
pandocproj-0.4.0.dist-info/LICENSE
pandocproj-0.4.0.dist-info/METADATA
pandocproj-0.4.0.dist-info/WHEEL
pandocproj-0.4.0.dist-info/entry_points.txt
pandocproj-0.4.0.dist-info/RECORD
