Metadata-Version: 2.1
Name: pandocproj
Version: 0.4.0
Summary: Reporting with Pandoc
Author: numenic
Author-email: nicolas@cordier.io
Requires-Python: >3.9,<3.12
Classifier: Programming Language :: Python :: 3
Classifier: Programming Language :: Python :: 3.10
Classifier: Programming Language :: Python :: 3.11
Requires-Dist: appdirs (>=1.4.4,<2.0.0)
Requires-Dist: inotify (>=0.2.10,<0.3.0)
Requires-Dist: pandoc (>=2.3,<3.0)
Requires-Dist: pandoc-eqnos (>=2.5.0,<3.0.0)
Requires-Dist: pandoc-fignos (>=2.4.0,<3.0.0)
Requires-Dist: pandoc-latex-admonition (>=1.3.3.2,<2.0.0.0)
Requires-Dist: pandoc-secnos (>=2.2.2,<3.0.0)
Requires-Dist: pandoc-tablenos (>=2.3.0,<3.0.0)
Requires-Dist: pandoc-xnos (>=2.5.0,<3.0.0)
Requires-Dist: pandocfilters (>=1.5.1,<2.0.0)
Requires-Dist: panflute (>=2.3.0,<3.0.0)
Requires-Dist: pantable (>=0.14.2,<0.15.0)
Requires-Dist: selenium (>=4.18.1,<5.0.0)
Requires-Dist: tabulate (>=0.9.0,<0.10.0)
